kedro_profile/__init__.py
kedro_profile/hook.py
kedro_profile-0.0.2.dist-info/METADATA
kedro_profile-0.0.2.dist-info/WHEEL
kedro_profile-0.0.2.dist-info/top_level.txt
kedro_profile-0.0.2.dist-info/RECORD
