Metadata-Version: 2.4
Name: kedro-profile
Version: 0.0.2
Summary: Identify the bottleneck of your Kedro Pipeline quickly
Author-email: Nok Lam Chan <mediumnok@gmail.com>
License: Apache2
Requires-Python: >=3.9.0
Requires-Dist: kedro>=0.18.5
Requires-Dist: pandas>=1.0.0
